template_string_generator/__init__.py
template_string_generator/app.py
template_string_generator-0.0.5.dist-info/LICENSE
template_string_generator-0.0.5.dist-info/METADATA
template_string_generator-0.0.5.dist-info/WHEEL
template_string_generator-0.0.5.dist-info/top_level.txt
template_string_generator-0.0.5.dist-info/RECORD
