Metadata-Version: 2.1
Name: template-string-generator
Version: 0.0.5
Summary: Generates all possible combinations of a string based on a given template
Home-page: https://github.com/PootisPenserHere/template_string_generator
Author: Jose Pablo Aramburo
Author-email: josepablo.aramburo@laziness.rocks
License: UNKNOWN
Platform: UNKNOWN
Classifier: Programming Language :: Python :: 3
Classifier: License :: OSI Approved :: GNU Affero General Public License v3
Classifier: Operating System :: OS Independent
Requires-Python: >=3.6
